ecrime/__init__.py
ecrime/ecrime.py
pyecrime-0.1.0.dist-info/LICENSE
pyecrime-0.1.0.dist-info/METADATA
pyecrime-0.1.0.dist-info/WHEEL
pyecrime-0.1.0.dist-info/entry_points.txt
pyecrime-0.1.0.dist-info/top_level.txt
pyecrime-0.1.0.dist-info/RECORD
